README.md
setup.py
bin/syntaxgym
syntaxgym/__init__.py
syntaxgym/agg_surprisals.py
syntaxgym/commands.py
syntaxgym/get_sentences.py
syntaxgym/prediction.py
syntaxgym/suite.py
syntaxgym/utils.py
syntaxgym.egg-info/PKG-INFO
syntaxgym.egg-info/SOURCES.txt
syntaxgym.egg-info/dependency_links.txt
syntaxgym.egg-info/requires.txt
syntaxgym.egg-info/top_level.txt
test/test_agg_surprisals.py
test/test_prediction.py
test/test_suite.py
test/test_utils.py