Metadata-Version: 1.2
Name: syntaxgym
Version: 0.5.5
Summary: Evaluate neural network language models on syntactic test suites
Home-page: https://syntaxgym.org
Author: Jon Gauthier
Author-email: jon@gauthiers.net
License: MIT
Keywords: language models,nlp,ai
Platform: UNKNOWN
Requires-Python: >=3.6
